[
  {
    "ContainingType": "NipedWebApi.Controllers.ClientController",
    "Method": "RegisterClientList",
    "RelativePath": "Client/register",
    "HttpMethod": "POST",
    "IsController": true,
    "Order": 0,
    "Parameters": [
      {
        "Name": "clientsAsJson",
        "Type": "System.String",
        "IsRequired": true
      }
    ],
    "ReturnTypes": [
      {
        "Type": "System.String",
        "MediaTypes": [
          "text/plain",
          "application/json",
          "text/json"
        ],
        "StatusCode": 200
      }
    ]
  },
  {
    "ContainingType": "NipedWebApi.Controllers.ClientController",
    "Method": "GetClinetsReport",
    "RelativePath": "Client/report",
    "HttpMethod": "GET",
    "IsController": true,
    "Order": 0,
    "Parameters": [],
    "ReturnTypes": [
      {
        "Type": "System.Collections.Generic.List\u00601[[NipedModel.ClientReportTO, NipedModel, Version=1.0.0.0, Culture=neutral, PublicKeyToken=null]]",
        "MediaTypes": [
          "text/plain",
          "application/json",
          "text/json"
        ],
        "StatusCode": 200
      }
    ]
  },
  {
    "ContainingType": "NipedWebApi.Controllers.GuidelineController",
    "Method": "GetGuideline",
    "RelativePath": "Guideline",
    "HttpMethod": "GET",
    "IsController": true,
    "Order": 0,
    "Parameters": [],
    "ReturnTypes": []
  },
  {
    "ContainingType": "NipedWebApi.Controllers.GuidelineController",
    "Method": "RegisterGuideline",
    "RelativePath": "Guideline/register",
    "HttpMethod": "POST",
    "IsController": true,
    "Order": 0,
    "Parameters": [
      {
        "Name": "guidelineAsJson",
        "Type": "System.String",
        "IsRequired": true
      }
    ],
    "ReturnTypes": [
      {
        "Type": "System.String",
        "MediaTypes": [
          "text/plain",
          "application/json",
          "text/json"
        ],
        "StatusCode": 200
      }
    ]
  }
]